udata_hydra/__init__.py
udata_hydra/analysis/__init__.py
udata_hydra/analysis/csv.py
udata_hydra/analysis/geojson.py
udata_hydra/analysis/helpers.py
udata_hydra/analysis/parquet.py
udata_hydra/analysis/resource.py
udata_hydra/app.py
udata_hydra/cli.py
udata_hydra/config_default.toml
udata_hydra/context.py
udata_hydra/crawl/__init__.py
udata_hydra/crawl/calculate_next_check.py
udata_hydra/crawl/check_resources.py
udata_hydra/crawl/helpers.py
udata_hydra/crawl/preprocess_check_data.py
udata_hydra/crawl/select_batch.py
udata_hydra/db/__init__.py
udata_hydra/db/check.py
udata_hydra/db/resource.py
udata_hydra/db/resource_exception.py
udata_hydra/logger.py
udata_hydra/migrations/__init__.py
udata_hydra/migrations/csv/20221205_initial_up_rev1.sql
udata_hydra/migrations/csv/20230130_drop_migrations.sql
udata_hydra/migrations/csv/20230206_datetime_aware.sql
udata_hydra/migrations/csv/20240827_add_indexes_column_to_tables_index_table.sql
udata_hydra/migrations/csv/20250610_migrate_resources_exception.sql
udata_hydra/migrations/csv/20250626_delete_datetime_iso_references.sql
udata_hydra/migrations/csv/20250902_delete_analyses_too_long_column_names.sql
udata_hydra/migrations/csv/20250911_add_deleted_column_to_tables_index.sql
udata_hydra/migrations/csv/20250916_add_dataset_id_to_tables_index.sql
udata_hydra/migrations/main/20221205_initial_up_rev1.sql
udata_hydra/migrations/main/20221206_rev1_up_rev2.sql
udata_hydra/migrations/main/20221206_rev2_up_rev3.sql
udata_hydra/migrations/main/20221208_rev3_up_rev4.sql
udata_hydra/migrations/main/20221208_rev4_up_rev5.sql
udata_hydra/migrations/main/20230119_rev5_up_rev6.sql
udata_hydra/migrations/main/20230121_rev6_up_rev7.sql
udata_hydra/migrations/main/20230121_rev7_up_rev8.sql
udata_hydra/migrations/main/20230130_drop_migrations.sql
udata_hydra/migrations/main/20230206_datetime_aware.sql
udata_hydra/migrations/main/20230515_rev8_up_rev9.sql
udata_hydra/migrations/main/20230606_rev9_up_rev10.sql
udata_hydra-10124.dist-info/WHEEL
udata_hydra-10124.dist-info/METADATA
udata_hydra-10124.dist-info/RECORD
