Metadata-Version: 2.3
Name: udata-hydra
Version: 10124
Summary: Async crawler and parsing service for data.gouv.fr
Author: Opendata Team
Author-email: Opendata Team <opendatateam@data.gouv.fr>
License: MIT
Requires-Dist: aiohttp>=3.10.3
Requires-Dist: asyncpg>=0.29.0
Requires-Dist: coloredlogs>=15.0.1
Requires-Dist: csv-detective==0.9.3.dev2010
Requires-Dist: dateparser>=1.1.7
Requires-Dist: humanfriendly>=10.0
Requires-Dist: json-stream>=2.3.3
Requires-Dist: marshmallow>=3.14.1
Requires-Dist: minicli>=0.5.3
Requires-Dist: minio>=7.2.8
Requires-Dist: progressist>=0.1.0
Requires-Dist: pyarrow>=16.1.0
Requires-Dist: python-magic>=0.4.25
Requires-Dist: python-slugify>=8.0.4
Requires-Dist: redis>=4.1.4
Requires-Dist: rq>=1.11.1
Requires-Dist: sentry-sdk>=2.10.0
Requires-Dist: sqlalchemy>=1.4.46
Requires-Dist: tippecanoe>=2.72.0
Requires-Dist: aiohttp-devtools>=1.0.post0 ; extra == 'dev'
Requires-Dist: aioresponses>=0.7.3 ; extra == 'dev'
Requires-Dist: gunicorn>=20.1.0 ; extra == 'dev'
Requires-Dist: mypy>=1.11.0 ; extra == 'dev'
Requires-Dist: nest-asyncio>=1.5.5 ; extra == 'dev'
Requires-Dist: pytest>=8.3.0 ; extra == 'dev'
Requires-Dist: pytest-asyncio>=1.1.0 ; extra == 'dev'
Requires-Dist: pytest-cov>=5.0.0 ; extra == 'dev'
Requires-Dist: pytest-mock>=3.7.0 ; extra == 'dev'
Requires-Dist: ruff>=0.9.3 ; extra == 'dev'
Requires-Python: >=3.11, <3.14
Provides-Extra: dev
